[1,["ecpdLyjvZBwrvm+cedCcQy","9aCQrAlEZCxrAS+cdb+tNl","1292024d8","e97GVMl6JHh5Ml5qEDdSGa","f0BIwQ8D5Ml7nTNQbh1YlS","29FYIk+N1GYaeWH/q1NxQO","1f119e695","4agzhAGHlLPIdbePiog6OM","79u5xk0bVLdqWdlhpYVM9R","c9qVLD9G9GGrcFvBmBOb4Y","12mW2AXTlM7bSejg9+9D88"],["node","_spriteFrame","_textureSetter","_parent","_N$normalSprite","_N$pressedSprite","_N$hoverSprite","_N$disabledSprite","root","data"],[["cc.Node",["_name","_active","_components","_prefab","_contentSize","_trs","_parent","_children","_color"],1,9,4,5,7,1,2,5],"cc.SpriteFrame",["cc.Sprite",["_sizeMode","_type","node","_materials","_spriteFrame"],1,1,3,6],["cc.Widget",["_alignFlags","_originalWidth","_originalHeight","alignMode","node"],-1,1],["cc.PrefabInfo",["fileId","root"],2,1],["cc.Label",["_lineHeight","_N$horizontalAlign","_N$verticalAlign","_N$overflow","_string","_enableWrapText","_N$cacheMode","_fontSize","node","_materials"],-5,1,3],["cc.Prefab",["_name"],2],["e7e3aAkLEdD5KHPN2yVVte0",["node"],3,1],["cc.BlockInputEvents",["node"],3,1],["cc.Button",["zoomScale","_N$transition","node","clickEvents","_N$normalColor","_N$pressedColor","_N$disabledColor","_N$target","_N$normalSprite","_N$pressedSprite","_N$hoverSprite","_N$disabledSprite"],1,1,9,5,5,5,1,6,6,6,6],["cc.ClickEvent",["_componentId","handler","target"],1,1],["744dcs4DCdNprNhG0xwq6FK",["_dataID","node"],2,1]],[[4,0,1,2],[0,0,6,2,3,4,5,2],[0,0,7,2,3,4,5,2],[0,0,6,7,2,3,4,5,2],[3,0,1,2,4,4],[3,3,0,1,2,4,5],[2,1,0,2,3,4,3],[2,0,2,3,4,2],[2,2,3,4,1],[9,0,1,2,3,4,5,6,7,8,9,10,11,3],[10,0,1,2,3],[5,4,0,5,1,2,3,6,8,9,8],[11,0,1,2],[6,0,2],[0,0,6,2,3,4,2],[0,0,1,6,7,2,3,4,5,3],[0,0,6,2,3,8,4,5,2],[7,0,1],[4,1,1],[8,0,1],[5,7,0,1,2,3,8,9,6]],[[[{"name":"link_bg","rect":[3,1877,676,80],"offset":[0,0],"originalSize":[676,80],"capInsets":[0,0,0,0]}],[1],0,[0],[2],[2]],[[{"name":"watch_again_icn","rect":[1574,1998,40,42],"offset":[0,0],"originalSize":[42,42],"capInsets":[0,0,0,0]}],[1],0,[0],[2],[6]],[[[13,"ReplayOverPrefab"],[2,"ReplayOverPrefab",[-4,-5,-6,-7],[[4,45,756,1638,-2],[17,-3]],[18,-1],[5,756,1638],[378,819,0,0,0,0,1,1,1,1]],[2,"Background",[-10,-11],[[6,1,0,-8,[5],6],[5,0,45,100,40,-9]],[0,"53aENkcVxFu6f2tkUE52wp",1],[5,328,103],[0,0,0,0,0,0,1,1,1,0]],[2,"Background",[-14,-15],[[6,1,0,-12,[14],15],[5,0,45,100,40,-13]],[0,"66O9Q9eWpKNpqs8kjaRZlJ",1],[5,328,103],[0,0,0,0,0,0,1,1,1,0]],[14,"bg",1,[[7,0,-16,[0],1],[4,45,678,2,-17],[19,-18]],[0,"ac1ZeC+ddEfaAW5O273Wrv",1],[5,756,1638]],[3,"rePlayBtn",1,[2],[[9,1.1,3,-19,[[10,"e7e3aAkLEdD5KHPN2yVVte0","rePlayBtnClick",1]],[4,4293322470],[4,4291348680],[4,3363338360],2,7,8,9,10]],[0,"c3GfROP/pJA5w8zqpfMZk7",1],[5,328,103],[-172.745,-432.986,0,0,0,0,1,1,1,1]],[1,"Label",2,[[11,"再次观看",45,false,1,1,2,1,-20,[4]],[12,"main.replay_again_one",-21]],[0,"7edHpPiKVPKL6npgqW40uv",1],[5,200,50],[18.896,0,0,0,0,0,1,1,1,1]],[3,"copyLinkBtn",1,[3],[[9,1.1,3,-22,[[10,"e7e3aAkLEdD5KHPN2yVVte0","copyLinkBtnClick",1]],[4,4293322470],[4,4291348680],[4,3363338360],3,16,17,18,19]],[0,"77aBlVupRL0aFZND0JtB3t",1],[5,328,103],[182.93,-432.986,0,0,0,0,1,1,1,1]],[1,"copyLabel",3,[[11,"复制链接",45,false,1,1,2,1,-23,[13]],[12,"main.pub_copy_link",-24]],[0,"4bKY0mKcRIiLaZRkxrg5tJ",1],[5,200,50],[18.896,0,0,0,0,0,1,1,1,1]],[15,"linkbg",false,1,[-26],[[7,0,-25,[21],22]],[0,"39QKYpBMtKDppY+hzjsd5t",1],[5,676,110],[0,-322.481,0,0,0,0,1,1,1,1]],[1,"New Sprite",2,[[8,-27,[2],3]],[0,"bbrwlGDGpLiroluxAK1U3A",1],[5,40,42],[-105.236,0,0,0,0,0,1,1,1,1]],[16,"iconspr",3,[[8,-28,[11],12]],[0,"d9rEgq6DNB576hZlG7y01C",1],[4,4288848546],[5,38,38],[-105.236,0,0,0,0,0,1,1,1,1]],[1,"linkLabel",9,[[20,28,30,1,1,2,-29,[20]]],[0,"2107D2i4pI5bKGiEdAU8Mu",1],[5,670,80.4],[0,7.826,0,0,0,0,1,1,1,1]]],0,[0,8,1,0,0,1,0,0,1,0,-1,4,0,-2,5,0,-3,7,0,-4,9,0,0,2,0,0,2,0,-1,10,0,-2,6,0,0,3,0,0,3,0,-1,11,0,-2,8,0,0,4,0,0,4,0,0,4,0,0,5,0,0,6,0,0,6,0,0,7,0,0,8,0,0,8,0,0,9,0,-1,12,0,0,10,0,0,11,0,0,12,0,9,1,2,3,5,3,3,7,29],[0,0,0,0,0,0,0,0,0,0,0,0,0,0,0,0,0,0,0,0,0,0,0],[-1,1,-1,1,-1,-1,1,4,5,6,7,-1,1,-1,-1,1,4,5,6,7,-1,-1,1],[0,7,0,8,0,0,1,1,3,4,5,0,9,0,0,1,1,3,4,5,0,0,10]],[[{"name":"active_btn_bg","rect":[350,1660,328,103],"offset":[0,0],"originalSize":[328,103],"capInsets":[0,0,0,0]}],[1],0,[0],[2],[2]]]]